{
	"info": {
		"_postman_id": "befa5dd1-62e1-43d5-9bcd-8e460c27472f",
		"name": "Jsonplaceholder.typecode",
		"schema": "https://schema.getpostman.com/json/collection/v2.0.0/collection.json"
	},
	"item": [
		{
			"name": "https://jsonplaceholder.typicode.com/posts?userId=1",
			"event": [
				{
					"listen": "test",
					"script": {
						"id": "f0d809b9-1b3a-4829-a4b9-bb2c3361653e",
						"exec": [
							"pm.test(\"Status code is 200\", function () {",
							"    pm.response.to.have.status(200);",
							"});",
							"",
							"pm.test(\"Body matches string\", function () {",
							"    pm.expect(pm.response.text()).to.include(\"quia et suscipit\");",
							"});",
							""
						],
						"type": "text/javascript"
					}
				}
			],
			"request": {
				"method": "GET",
				"header": [],
				"url": {
					"raw": "https://jsonplaceholder.typicode.com/posts?userId=1",
					"protocol": "https",
					"host": [
						"jsonplaceholder",
						"typicode",
						"com"
					],
					"path": [
						"posts"
					],
					"query": [
						{
							"key": "userId",
							"value": "1"
						}
					]
				}
			},
			"response": []
		}
	],
	"protocolProfileBehavior": {}
}